variamotif/__init__.py
variamotif/main.py
variamotif-1.0.1.dist-info/LICENSE
variamotif-1.0.1.dist-info/METADATA
variamotif-1.0.1.dist-info/WHEEL
variamotif-1.0.1.dist-info/entry_points.txt
variamotif-1.0.1.dist-info/top_level.txt
variamotif-1.0.1.dist-info/RECORD
